README.md
setup.cfg
setup.py
mtunn/__init__.py
mtunn/__main__.py
mtunn.egg-info/PKG-INFO
mtunn.egg-info/SOURCES.txt
mtunn.egg-info/dependency_links.txt
mtunn.egg-info/requires.txt
mtunn.egg-info/top_level.txt