Metadata-Version: 2.1
Name: mtunn
Version: 1.2.9
Summary: Easy open tcp, http, https ports from localhost to internet.
Home-page: https://github.com/mishakorzik/mtunn
Author: MishaKorzhik_He1Zen
Author-email: developer.mishakorzhik@gmail.com
License: Apache 2.0
Project-URL: Bug Tracker, https://github.com/mishakorzik/mtunn/issues
Project-URL: Donate, https://www.buymeacoffee.com/misakorzik
Keywords: linux,windows,make,mtunn,tcp,http,https,open,port,easy,tunnel,alpha,beta,stable,pip,pypi,ping,firewall,domain,vpn,tor,console,control,ipv4,ipv6
Classifier: Development Status :: 5 - Production/Stable
Classifier: License :: OSI Approved :: Apache Software License
Classifier: Operating System :: OS Independent
Classifier: Programming Language :: Python
Classifier: Programming Language :: Python :: 3
Classifier: Programming Language :: Python :: 3.6
Classifier: Programming Language :: Python :: 3.7
Classifier: Programming Language :: Python :: 3.8
Classifier: Programming Language :: Python :: 3.9
Classifier: Programming Language :: Python :: 3.10
Classifier: Programming Language :: Python :: 3.11
Classifier: Programming Language :: Python :: 3.12
Classifier: Programming Language :: Python :: 3.13
Classifier: Programming Language :: Python :: 3.14
Classifier: Programming Language :: Python :: Implementation :: CPython
Classifier: Programming Language :: Python :: Implementation :: PyPy
Classifier: Topic :: Internet
Classifier: Topic :: System :: Networking
Classifier: Environment :: Console
Requires-Python: >=3.6
Requires-Dist: cryptography>=3.2
Requires-Dist: lockis>=1.0.2
Requires-Dist: windows-curses>=2.3.0; sys_platform == "win32"
